mediathek_py/__init__.py
mediathek_py/cli.py
mediathek_py/client.py
mediathek_py/docs.md
mediathek_py/exceptions.py
mediathek_py/models.py
mediathek_py/series.py
mediathek_py-0.1.3.dist-info/METADATA
mediathek_py-0.1.3.dist-info/WHEEL
mediathek_py-0.1.3.dist-info/entry_points.txt
mediathek_py-0.1.3.dist-info/licenses/LICENSE
mediathek_py-0.1.3.dist-info/RECORD
