Metadata-Version: 2.4
Name: mediathek-py
Version: 0.1.3
Summary: Python API wrapper and CLI for MediathekViewWeb
Project-URL: Repository, https://github.com/maxboettinger/mediathek-py
Project-URL: Homepage, https://github.com/maxboettinger/mediathek-py
Author-email: Max Böttinger <max@bttngr.de>
License: MIT
License-File: LICENSE
Keywords: api-wrapper,ard,arte,cli,downloader,german-tv,mediathek,mediathekview,zdf
Classifier: Development Status :: 4 - Beta
Classifier: Environment :: Console
Classifier: Intended Audience :: End Users/Desktop
Classifier: License :: OSI Approved :: MIT License
Classifier: Operating System :: OS Independent
Classifier: Programming Language :: Python :: 3
Classifier: Programming Language :: Python :: 3.12
Classifier: Topic :: Internet :: WWW/HTTP
Classifier: Topic :: Multimedia :: Video
Classifier: Topic :: Utilities
Requires-Python: >=3.12
Requires-Dist: click
Requires-Dist: httpx
Requires-Dist: pydantic
Requires-Dist: rich
